pymontasir.py
pymontasir-0.0.1.dist-info/LICENSE.txt
pymontasir-0.0.1.dist-info/METADATA
pymontasir-0.0.1.dist-info/WHEEL
pymontasir-0.0.1.dist-info/top_level.txt
pymontasir-0.0.1.dist-info/RECORD
